jit_env/__init__.py
jit_env/_compat_test.py
jit_env/_core.py
jit_env/_core_test.py
jit_env/_specs_test.py
jit_env/_test_compat.py
jit_env/_test_core.py
jit_env/_test_specs.py
jit_env/_test_wrappers.py
jit_env/_wrappers_test.py
jit_env/compat.py
jit_env/py.typed
jit_env/specs.py
jit_env/version.py
jit_env/wrappers.py
jit_env-0.1.5.dist-info/LICENSE
jit_env-0.1.5.dist-info/METADATA
jit_env-0.1.5.dist-info/WHEEL
jit_env-0.1.5.dist-info/top_level.txt
jit_env-0.1.5.dist-info/RECORD
