Metadata-Version: 2.1
Name: jit-env
Version: 0.1.5
Summary: A Jax interface for Reinforcement Learning environments.
Home-page: https://github.com/joeryjoery/jit_env
Author: Joery A. de Vries
Author-email: J.A.deVries@tudelft.nl
License: MIT
Keywords: reinforcement-learning python machine learning jax
Classifier: Operating System :: OS Independent
Classifier: License :: OSI Approved :: MIT License
Classifier: Programming Language :: Python :: 3.9
Classifier: Programming Language :: Python :: 3.10
Classifier: Programming Language :: Python :: 3.11
Classifier: Topic :: Software Development :: Testing :: Mocking
Classifier: Topic :: Software Development :: Testing :: Unit
Requires-Python: >=3.9
License-File: LICENSE
Requires-Dist: jax >=0.4.6
Requires-Dist: chex >=0.1.7
Requires-Dist: jaxtyping >=0.2.14
Provides-Extra: dev
Requires-Dist: pytest >=7.1.2 ; extra == 'dev'
Requires-Dist: pytest-cov >=4.0.0 ; extra == 'dev'
Requires-Dist: twine >=4.0.2 ; extra == 'dev'
Requires-Dist: wheel >=0.37.1 ; extra == 'dev'
Requires-Dist: tox >=4.4.11 ; extra == 'dev'
Requires-Dist: flake8 >=6.0.0 ; extra == 'dev'
Requires-Dist: mypy >=1.2.0 ; extra == 'dev'
Requires-Dist: dm-env >=1.5 ; extra == 'dev'
Requires-Dist: gymnasium >=0.28.0 ; extra == 'dev'
